onem/__init__.py
onem/common.py
onem/forms.py
onem/menus.py
onem_py-0.0.3.dist-info/LICENSE
onem_py-0.0.3.dist-info/METADATA
onem_py-0.0.3.dist-info/WHEEL
onem_py-0.0.3.dist-info/top_level.txt
onem_py-0.0.3.dist-info/RECORD
