Metadata-Version: 2.1
Name: onem-py
Version: 0.0.3
Summary: Defines the JSON structure accepted by ONEm platform.
Home-page: https://github.com/mvnm/onem-py
Author: Marius Vigariu
Author-email: marius.vigariu@onem.com
License: UNKNOWN
Platform: UNKNOWN
Classifier: Programming Language :: Python :: 3
Classifier: License :: OSI Approved :: Apache Software License
Classifier: Operating System :: OS Independent
